qupiato/cli/config.py
qupiato/cli/hooktest.py
qupiato/cli/main.py
qupiato/cli/utils.py
pyqqq_cli-0.4.22.dist-info/METADATA
pyqqq_cli-0.4.22.dist-info/WHEEL
pyqqq_cli-0.4.22.dist-info/entry_points.txt
pyqqq_cli-0.4.22.dist-info/RECORD
