Metadata-Version: 2.4
Name: pyqqq-cli
Version: 0.4.22
Summary: CLI tool for controlling strategies deployed on the PyQQQ platform.
License: MIT
Author: PyQQQ team
Author-email: pyqqq.cs@gmail.com
Requires-Python: >=3.10,<4.0
Classifier: License :: OSI Approved :: MIT License
Classifier: Programming Language :: Python :: 3
Classifier: Programming Language :: Python :: 3.10
Classifier: Programming Language :: Python :: 3.11
Classifier: Programming Language :: Python :: 3.12
Classifier: Programming Language :: Python :: 3.13
Classifier: Programming Language :: Python :: 3.14
Requires-Dist: click (>=8.1.7,<9.0.0)
Requires-Dist: freezegun (>=1.5.1,<2.0.0)
Requires-Dist: openai (>=1.35.10,<2.0.0)
Requires-Dist: pylint (>=3.2.5,<4.0.0)
Requires-Dist: pyqqq (>=0.12,<0.13)
Requires-Dist: python-dotenv (>=1.0.1,<2.0.0)
Requires-Dist: pyyaml (>=6.0.1,<7.0.0)
Requires-Dist: requests (>=2.31.0,<3.0.0)
Requires-Dist: websockets (>=12.0,<13.0)
Project-URL: Documentation, https://qupiato-sdk-18secs-cf54ebea1b14b422537daf0462fb86d68f4582d064a4.gitlab.io
